nbxmssql/MSSQL_helper.py
nbxmssql/__init__.py
nbxmssql-0.1.2.dist-info/METADATA
nbxmssql-0.1.2.dist-info/WHEEL
nbxmssql-0.1.2.dist-info/top_level.txt
nbxmssql-0.1.2.dist-info/RECORD
